{
  "Algorithm": [
    "bypass"
  ],
  "Mix": [
    "*gain*",
    "*feedback*",
    "*normalize*"
  ],
  "Record": [
    "*record*",
    "*buffer size*",
    "*normalize*"
  ],
  "Modulation": [
    "*LFO*",
    "Attack*",
    "Release*",
    "*->*",
    "Pitch quantize",
    "Sustain mode"
  ],
  "Grains": [
    "shape",
    "spawn mode",
    "* spread",
    "* mean",
    "reverse",
    "*grain*",
    "natural pitch",
    "opacity"
  ],
  "Drone 1": [
    "*drone 1*"
  ],
  "Drone 2": [
    "*drone 2*"
  ],
  "Drone 3": [
    "*drone 3*"
  ],
  "Setup": [
    "*midi*",
    "*mpe*",
    "*channel*",
    "bend*",
    "delay unit"
  ],
  "CV/Gate": [
    "*gate*"
  ],
  "Routing": [
    "*output*",
    "*input*",
    "*delay mean*"
  ],
  "Other": ["*"]
}